{"chunk_definitions":[{"chunk_id":"csetup_chunk","chunk_label":"setup","document_id":"1DA53E6","expansion_state":0,"options":{"engine":"r","include":false,"label":"setup"},"row":65,"row_count":1,"visible":true},{"chunk_id":"c8j0470hjr32d","chunk_label":"1_load_us_data","document_id":"1DA53E6","expansion_state":0,"options":{"engine":"r","label":"1_load_us_data"},"row":76,"row_count":1,"visible":true},{"chunk_id":"c8dchcf86oo0t","chunk_label":"1 bivariate model","document_id":"1DA53E6","expansion_state":0,"options":{"engine":"r","label":"1 bivariate model"},"row":83,"row_count":1,"visible":true},{"chunk_id":"c8f7l24ju9tu6","chunk_label":"1 aux1","document_id":"1DA53E6","expansion_state":0,"options":{"engine":"r","label":"1 aux1"},"row":95,"row_count":1,"visible":true},{"chunk_id":"cixggepowr61y","chunk_label":"1 residuals aux1","document_id":"1DA53E6","expansion_state":0,"options":{"engine":"r","label":"1 residuals aux1"},"row":105,"row_count":1,"visible":true},{"chunk_id":"c4jh5bf6etb2g","chunk_label":"1 aux2","document_id":"1DA53E6","expansion_state":0,"options":{"engine":"r","label":"1 aux2"},"row":114,"row_count":1,"visible":true},{"chunk_id":"cny6purglfzre","chunk_label":"1 residuals aux2","document_id":"1DA53E6","expansion_state":0,"options":{"engine":"r","label":"1 residuals aux2"},"row":122,"row_count":1,"visible":true},{"chunk_id":"cy1lcaa4o2lz7","chunk_label":"1 aux3","document_id":"1DA53E6","expansion_state":0,"options":{"engine":"r","label":"1 aux3"},"row":132,"row_count":1,"visible":true},{"chunk_id":"ck7lnge0rzzh6","chunk_label":"1 summary aux3","document_id":"1DA53E6","expansion_state":0,"options":{"engine":"r","label":"1 summary aux3"},"row":138,"row_count":1,"visible":true},{"chunk_id":"cwp4sjex17nu5","chunk_label":"1 lm function","document_id":"1DA53E6","expansion_state":0,"options":{"engine":"r","label":"1 lm function"},"row":149,"row_count":1,"visible":true},{"chunk_id":"c74m7t5s59dda","chunk_label":"1 comparison","document_id":"1DA53E6","expansion_state":0,"options":{"engine":"r","label":"1 comparison"},"row":155,"row_count":1,"visible":true},{"chunk_id":"cqdj0w0c58fky","chunk_label":"2_1 Load the data","document_id":"1DA53E6","expansion_state":0,"options":{"engine":"r","label":"2_1 Load the data"},"row":179,"row_count":1,"visible":true},{"chunk_id":"cmdbuy8l99igf","chunk_label":"2_1 Exploratory Data Analysis","document_id":"1DA53E6","expansion_state":0,"options":{"engine":"r","label":"2_1 Exploratory Data Analysis"},"row":207,"row_count":1,"visible":true},{"chunk_id":"cq35h4nbgtiff","chunk_label":"2_1 A first comparison","document_id":"1DA53E6","expansion_state":0,"options":{"engine":"r","label":"2_1 A first comparison"},"row":227,"row_count":1,"visible":true},{"chunk_id":"cbg24no5xydzj","chunk_label":"2_1 A naive regression model","document_id":"1DA53E6","expansion_state":0,"options":{"engine":"r","label":"2_1 A naive regression model"},"row":235,"row_count":1,"visible":true},{"chunk_id":"cdkumzwvx04gd","chunk_label":"2_1 Controlling for a confounder","document_id":"1DA53E6","expansion_state":0,"options":{"engine":"r","label":"2_1 Controlling for a confounder"},"row":247,"row_count":1,"visible":true},{"chunk_id":"cdcwp9mobqy9y","chunk_label":"2_1 Coloring the dots","document_id":"1DA53E6","expansion_state":0,"options":{"engine":"r","label":"2_1 Coloring the dots"},"row":272,"row_count":1,"visible":true},{"chunk_id":"ch6grmaw65aqm","chunk_label":"2_2 Loading the data","document_id":"1DA53E6","expansion_state":0,"options":{"engine":"r","label":"2_2 Loading the data"},"row":285,"row_count":1,"visible":true},{"chunk_id":"cpptq0wvc6yh7","chunk_label":"2_2 Exploratory Data Analysis","document_id":"1DA53E6","expansion_state":0,"options":{"engine":"r","label":"2_2 Exploratory Data Analysis"},"row":309,"row_count":1,"visible":true},{"chunk_id":"cjx4dlt87tijz","chunk_label":"2_2 First regression","document_id":"1DA53E6","expansion_state":0,"options":{"engine":"r","label":"2_2 First regression"},"row":318,"row_count":1,"visible":true},{"chunk_id":"cd6snj5qw3cz1","chunk_label":"2_2 Controlling for interest","document_id":"1DA53E6","expansion_state":0,"options":{"engine":"r","label":"2_2 Controlling for interest"},"row":325,"row_count":1,"visible":true},{"chunk_id":"cgztcfr3kj362","chunk_label":"2_3 Loading the data","document_id":"1DA53E6","expansion_state":0,"options":{"engine":"r","label":"2_3 Loading the data"},"row":341,"row_count":1,"visible":true},{"chunk_id":"c6v5m3gqktzre","chunk_label":"2_3 Exploratory Data Analysis","document_id":"1DA53E6","expansion_state":0,"options":{"engine":"r","label":"2_3 Exploratory Data Analysis"},"row":367,"row_count":1,"visible":true},{"chunk_id":"caw7cel2f7v6i","chunk_label":"2_3 First regression","document_id":"1DA53E6","expansion_state":0,"options":{"engine":"r","label":"2_3 First regression"},"row":376,"row_count":1,"visible":true},{"chunk_id":"cmia87yj5sh6z","chunk_label":"2_3 Controlling for vote","document_id":"1DA53E6","expansion_state":0,"options":{"engine":"r","label":"2_3 Controlling for vote"},"row":383,"row_count":1,"visible":true},{"chunk_id":"cy2vgxqjlr4xc","chunk_label":"load exercise data","document_id":"1DA53E6","expansion_state":0,"options":{"engine":"r","label":"load exercise data"},"row":408,"row_count":1,"visible":true},{"chunk_id":"c9hglebrljurm","chunk_label":"exercise plots","document_id":"1DA53E6","expansion_state":0,"options":{"engine":"r","label":"exercise plots"},"row":446,"row_count":1,"visible":true}],"chunk_rendered_width":400,"doc_write_time":1610361845}